mcpagentai/__init__.py
mcpagentai/__main__.py
mcpagentai/defs.py
mcpagentai/main.py
mcpagentai/server.py
mcpagentai/core/__init__.py
mcpagentai/core/agent_base.py
mcpagentai/core/logging.py
mcpagentai/core/multi_tool_agent.py
mcpagentai/tools/__init__.py
mcpagentai/tools/calculator_agent.py
mcpagentai/tools/crypto_agent.py
mcpagentai/tools/currency_agent.py
mcpagentai/tools/dictionary_agent.py
mcpagentai/tools/stock_agent.py
mcpagentai/tools/time_agent.py
mcpagentai/tools/weather_agent.py
mcpagentai/tools/eliza/__init__.py
mcpagentai/tools/eliza/agent.py
mcpagentai/tools/eliza/mcp_agent.py
mcpagentai/tools/eliza/scripts/monitor.sh
mcpagentai/tools/eliza/scripts/run.sh
mcpagentai/tools/eliza/scripts/setup.sh
mcpagentai/tools/twitter/__init__.py
mcpagentai/tools/twitter/agent.py
mcpagentai/tools/twitter/agent_client_wrapper.py
mcpagentai/tools/twitter/api_agent.py
mcpagentai/tools/twitter/query_handler.py
mcpagentai/tools/twitter/handlers/__init__.py
mcpagentai/tools/twitter/handlers/crypto_handler.py
mcpagentai/tools/twitter/handlers/currency_handler.py
mcpagentai/tools/twitter/handlers/dictionary_handler.py
mcpagentai/tools/twitter/handlers/stock_handler.py
mcpagentai/tools/twitter/handlers/time_handler.py
mcpagentai/tools/twitter/handlers/weather_handler.py
mcpagentai-1.0.0.dist-info/METADATA
mcpagentai-1.0.0.dist-info/WHEEL
mcpagentai-1.0.0.dist-info/entry_points.txt
mcpagentai-1.0.0.dist-info/licenses/LICENSE
mcpagentai-1.0.0.dist-info/RECORD
