Metadata-Version: 2.4
Name: mcpagentai
Version: 1.0.0
Summary: A generic multi-tool MCP Agent with Twitter, Eliza, Weather, Dictionary, Calculator, etc.
Author-email: MCPAgentAIDev <dev@mcpagentai.com>
License: MIT
License-File: LICENSE
Keywords: LLM,agent,aiagent,calculator,currency,dictionary,mcp,time,twitter,weather
Classifier: Development Status :: 3 - Alpha
Classifier: Intended Audience :: Developers
Classifier: License :: OSI Approved :: MIT License
Classifier: Programming Language :: Python :: 3
Classifier: Programming Language :: Python :: 3.12
Requires-Python: >=3.12
Requires-Dist: anthropic
Requires-Dist: mcp
Requires-Dist: pydantic
Requires-Dist: requests
Requires-Dist: tweepy
